{
  "name": "SvelteKit",
  "package": "app-sveltekit",
  "isFocused": true,
  "type": "runtime-app",
  "timingMeasuredAt": "2026-07-23T10:53:04.496Z",
  "runner": "Depot depot-ubuntu-24.04 GitHub Actions runner (2 CPUs, 8 GB RAM, 100 GB disk, 2 GB disk accelerator)",
  "frameworkVersion": "2.49.4",
  "order": 7,
  "clientSideRenderedTests": {
    "firstPaintMs": 126.6,
    "fcpMs": 126.62,
    "inpMs": 13.65,
    "runs": 5
  },
  "ssrRequestThroughputTests": {
    "opsPerSec": 436,
    "avgLatencyMs": 2.348,
    "medianLatencyMs": 2.229,
    "samples": 4259,
    "bodySizeKb": 183.53,
    "duplicationFactor": 2
  },
  "serverSideRenderedTests": {
    "firstPaintMs": 93.8,
    "fcpMs": 93.67,
    "inpMs": 16.05,
    "runs": 5
  },
  "ssrLoadTests": {
    "peakWorkers": 5,
    "peakRequestsPerSec": 494.8,
    "peakAvgLatencyMs": 9.73,
    "peakP50LatencyMs": 8,
    "peakP75LatencyMs": 12,
    "peakP90LatencyMs": 13,
    "peakP99LatencyMs": 19,
    "totalRequests": 15812,
    "totalErrors": 0,
    "stages": [
      {
        "workers": 1,
        "durationMs": 5010,
        "requests": 1469,
        "errors": 0,
        "requestsPerSec": 293.8,
        "avgLatencyMs": 2.86,
        "medianLatencyMs": 2,
        "p50LatencyMs": 2,
        "p75LatencyMs": 3,
        "p90LatencyMs": 3,
        "p99LatencyMs": 10,
        "maxLatencyMs": 14,
        "bytesPerSec": 81939660.8
      },
      {
        "workers": 5,
        "durationMs": 5000,
        "requests": 2474,
        "errors": 0,
        "requestsPerSec": 494.8,
        "avgLatencyMs": 9.73,
        "medianLatencyMs": 8,
        "p50LatencyMs": 8,
        "p75LatencyMs": 12,
        "p90LatencyMs": 13,
        "p99LatencyMs": 19,
        "maxLatencyMs": 25,
        "bytesPerSec": 138012262.4
      },
      {
        "workers": 10,
        "durationMs": 5000,
        "requests": 2470,
        "errors": 0,
        "requestsPerSec": 494,
        "avgLatencyMs": 19.75,
        "medianLatencyMs": 21,
        "p50LatencyMs": 21,
        "p75LatencyMs": 22,
        "p90LatencyMs": 24,
        "p99LatencyMs": 33,
        "maxLatencyMs": 80,
        "bytesPerSec": 137789440
      },
      {
        "workers": 25,
        "durationMs": 5000,
        "requests": 2394,
        "errors": 0,
        "requestsPerSec": 478.8,
        "avgLatencyMs": 51.43,
        "medianLatencyMs": 48,
        "p50LatencyMs": 48,
        "p75LatencyMs": 55,
        "p90LatencyMs": 66,
        "p99LatencyMs": 91,
        "maxLatencyMs": 347,
        "bytesPerSec": 133582028.8
      },
      {
        "workers": 50,
        "durationMs": 5000,
        "requests": 2391,
        "errors": 0,
        "requestsPerSec": 478.2,
        "avgLatencyMs": 102.81,
        "medianLatencyMs": 100,
        "p50LatencyMs": 100,
        "p75LatencyMs": 111,
        "p90LatencyMs": 132,
        "p99LatencyMs": 406,
        "maxLatencyMs": 1077,
        "bytesPerSec": 133391974.4
      },
      {
        "workers": 100,
        "durationMs": 5010,
        "requests": 2327,
        "errors": 0,
        "requestsPerSec": 465.4,
        "avgLatencyMs": 183.9,
        "medianLatencyMs": 122,
        "p50LatencyMs": 122,
        "p75LatencyMs": 169,
        "p90LatencyMs": 233,
        "p99LatencyMs": 2432,
        "maxLatencyMs": 4890,
        "bytesPerSec": 129820262.4
      },
      {
        "workers": 200,
        "durationMs": 5010,
        "requests": 2287,
        "errors": 0,
        "requestsPerSec": 457.4,
        "avgLatencyMs": 184.38,
        "medianLatencyMs": 127,
        "p50LatencyMs": 127,
        "p75LatencyMs": 166,
        "p90LatencyMs": 204,
        "p99LatencyMs": 2543,
        "maxLatencyMs": 4892,
        "bytesPerSec": 127605145.6
      }
    ]
  },
  "browserVersion": "Google Chrome 150.0.7871.46"
}
