{
  "name": "SolidStart",
  "package": "starter-solid-start",
  "type": "starter-kit",
  "prodDependencies": 5,
  "devDependencies": 0,
  "timingMeasuredAt": "2026-02-19T12:55:04.958Z",
  "runner": "ubuntu-latest",
  "installTimeMs": 3935,
  "nodeModulesSize": 168337408,
  "nodeModulesSizeProdOnly": 168337408,
  "coldBuildTimeMs": 9919,
  "warmBuildTimeMs": 9551,
  "buildOutputSize": 888832,
  "frameworkVersion": "1.2.1",
  "avgInstallTimeMs": 3066.2,
  "minInstallTimeMs": 2586,
  "maxInstallTimeMs": 4638,
  "coldBuildTime": {
    "avgMs": 9280,
    "minMs": 9117,
    "maxMs": 9483
  },
  "warmBuildTime": {
    "avgMs": 9242.4,
    "minMs": 9106,
    "maxMs": 9657
  },
  "installTime": {
    "avgMs": 2444.2,
    "minMs": 2309,
    "maxMs": 2813
  },
  "order": 6
}
