{
  "timingMeasuredAt": "2026-06-28T12:20:38.442Z",
  "runner": "ubuntu-latest",
  "frameworkVersion": "unknown",
  "installTime": {
    "avgMs": 531.2,
    "minMs": 509,
    "maxMs": 572
  },
  "nodeModulesSize": 30572544,
  "nodeModulesSizeProdOnly": 3522560,
  "coldBuildTime": {
    "avgMs": 366.4,
    "minMs": 356,
    "maxMs": 388
  },
  "warmBuildTime": {
    "avgMs": 364.6,
    "minMs": 358,
    "maxMs": 379
  },
  "buildOutputSize": 12288,
  "prodDependencies": 2,
  "devDependencies": 2,
  "duplicateDependencies": 0,
  "depInstallSize": 28724892,
  "e18eMessages": [],
  "vendoredCoreJsSize": 0,
  "vendoredCoreJsUnnecessaryModules": []
}
